AneMetro-0.0.1.dev26.dist-info/DESCRIPTION.rst
AneMetro-0.0.1.dev26.dist-info/METADATA
AneMetro-0.0.1.dev26.dist-info/RECORD
AneMetro-0.0.1.dev26.dist-info/WHEEL
AneMetro-0.0.1.dev26.dist-info/entry_points.txt
AneMetro-0.0.1.dev26.dist-info/metadata.json
AneMetro-0.0.1.dev26.dist-info/top_level.txt
anemetro/__init__.py
anemetro/anemetro.py
anemetro/command_line.py
anemetro/models.py
