Metadata-Version: 2.0
Name: AneMetro
Version: 0.0.1.dev26
Summary: Static site generator wrapper using MeetUp as data source.
Home-page: https://github.com/pypa/sampleproject
Author: David Roberts
Author-email: pypi@teapotcoder.com
License: MIT
Keywords: anemetro meetup static
Platform: UNKNOWN
Classifier: Development Status :: 3 - Alpha
Classifier: Intended Audience :: Developers
Classifier: Topic :: Software Development :: Build Tools
Classifier: License :: OSI Approved :: MIT License
Classifier: Programming Language :: Python :: 2
Classifier: Programming Language :: Python :: 3
Classifier: Programming Language :: Python :: 3.3
Classifier: Programming Language :: Python :: 3.4
Classifier: Programming Language :: Python :: 3.5
Requires-Dist: AneMetroHexo
Requires-Dist: meetup.api
Requires-Dist: pytz
Requires-Dist: requests
Requires-Dist: reyaml
